[
  {
    "fechaHora": "2024-10-09 16:32:45",
    "mensajeError": "Error al obtener la cotizaci贸n: Error en la respuesta de la API: C贸digo 404",
    "inputUsuario": "0.0003"
  },
  {
    "fechaHora": "2024-10-09 16:32:50",
    "mensajeError": "Error al obtener la cotizaci贸n: Error en la respuesta de la API: C贸digo 404",
    "inputUsuario": "321321658"
  },
  {
    "fechaHora": "2024-10-09 16:33:03",
    "mensajeError": "Error: For input string: \"2. 03326.3\"",
    "inputUsuario": "2. 03326.3"
  }
]